{
  "title": "Total Fertility Rate by Country (2025)",
  "data": [
    {"country": "Chad", "total_fertility_rate": 5.94},
    {"country": "Somalia", "total_fertility_rate": 5.91},
    {"country": "DR Congo", "total_fertility_rate": 5.90},
    {"country": "Central African Republic", "total_fertility_rate": 5.81},
    {"country": "Niger", "total_fertility_rate": 5.79},
    {"country": "Mali", "total_fertility_rate": 5.42},
    {"country": "Angola", "total_fertility_rate": 4.95},
    {"country": "Burundi", "total_fertility_rate": 4.68},
    {"country": "Afghanistan", "total_fertility_rate": 4.66},
    {"country": "Mozambique", "total_fertility_rate": 4.62},
    {"country": "Mauritania", "total_fertility_rate": 4.56},
    {"country": "Mayotte (France)", "total_fertility_rate": 4.50},
    {"country": "Tanzania", "total_fertility_rate": 4.47},
    {"country": "Benin", "total_fertility_rate": 4.42},
    {"country": "Yemen", "total_fertility_rate": 4.41},
    {"country": "Nigeria", "total_fertility_rate": 4.30},
    {"country": "Sudan", "total_fertility_rate": 4.19},
    {"country": "Cameroon", "total_fertility_rate": 4.19},
    {"country": "Ivory Coast", "total_fertility_rate": 4.17},
    {"country": "Togo", "total_fertility_rate": 4.07},
    {"country": "Uganda", "total_fertility_rate": 4.06},
    {"country": "Congo", "total_fertility_rate": 4.05},
    {"country": "Guinea", "total_fertility_rate": 4.04},
    {"country": "Equatorial Guinea", "total_fertility_rate": 4.04},
    {"country": "Burkina Faso", "total_fertility_rate": 4.01},
    {"country": "Zambia", "total_fertility_rate": 3.97},
    {"country": "Madagascar", "total_fertility_rate": 3.85},
    {"country": "Ethiopia", "total_fertility_rate": 3.81},
    {"country": "Gambia", "total_fertility_rate": 3.80},
    {"country": "Liberia", "total_fertility_rate": 3.79},
    {"country": "Comoros", "total_fertility_rate": 3.76},
    {"country": "Samoa", "total_fertility_rate": 3.75},
    {"country": "Senegal", "total_fertility_rate": 3.71},
    {"country": "South Sudan", "total_fertility_rate": 3.71},
    {"country": "Guinea-Bissau", "total_fertility_rate": 3.68},
    {"country": "Zimbabwe", "total_fertility_rate": 3.62},
    {"country": "Eritrea", "total_fertility_rate": 3.61},
    {"country": "Sierra Leone", "total_fertility_rate": 3.61},
    {"country": "Rwanda", "total_fertility_rate": 3.59},
    {"country": "Gabon", "total_fertility_rate": 3.54},
    {"country": "Vanuatu", "total_fertility_rate": 3.53},
    {"country": "Malawi", "total_fertility_rate": 3.53},
    {"country": "São Tomé and Príncipe", "total_fertility_rate": 3.53},
    {"country": "Pakistan", "total_fertility_rate": 3.50},
    {"country": "Solomon Islands", "total_fertility_rate": 3.47},
    {"country": "Uzbekistan", "total_fertility_rate": 3.45},
    {"country": "Ghana", "total_fertility_rate": 3.30},
    {"country": "French Guiana (France)", "total_fertility_rate": 3.29},
    {"country": "Nauru", "total_fertility_rate": 3.25},
    {"country": "Palestine", "total_fertility_rate": 3.19},
    {"country": "Iraq", "total_fertility_rate": 3.17},
    {"country": "Namibia", "total_fertility_rate": 3.17},
    {"country": "Tuvalu", "total_fertility_rate": 3.14},
    {"country": "Kenya", "total_fertility_rate": 3.12},
    {"country": "Kiribati", "total_fertility_rate": 3.09},
    {"country": "Tonga", "total_fertility_rate": 3.07},
    {"country": "Papua New Guinea", "total_fertility_rate": 3.03},
    {"country": "Tajikistan", "total_fertility_rate": 2.99},
    {"country": "Kazakhstan", "total_fertility_rate": 2.95},
    {"country": "Marshall Islands", "total_fertility_rate": 2.82},
    {"country": "Israel", "total_fertility_rate": 2.75},
    {"country": "Kyrgyzstan", "total_fertility_rate": 2.75},
    {"country": "Guam (US)", "total_fertility_rate": 2.71},
    {"country": "Egypt", "total_fertility_rate": 2.71},
    {"country": "Micronesia", "total_fertility_rate": 2.71},
    {"country": "Eswatini", "total_fertility_rate": 2.68},
    {"country": "Algeria", "total_fertility_rate": 2.67},
    {"country": "Botswana", "total_fertility_rate": 2.66},
    {"country": "Syria", "total_fertility_rate": 2.66},
    {"country": "Lesotho", "total_fertility_rate": 2.64},
    {"country": "Saint Martin (France)", "total_fertility_rate": 2.63},
    {"country": "Turkmenistan", "total_fertility_rate": 2.63},
    {"country": "Haiti", "total_fertility_rate": 2.59},
    {"country": "Mongolia", "total_fertility_rate": 2.59},
    {"country": "Djibouti", "total_fertility_rate": 2.58},
    {"country": "Jordan", "total_fertility_rate": 2.57},
    {"country": "Tokelau (NZ)", "total_fertility_rate": 2.57},
    {"country": "Timor-Leste", "total_fertility_rate": 2.56},
    {"country": "Cambodia", "total_fertility_rate": 2.51},
    {"country": "Bolivia", "total_fertility_rate": 2.50},
    {"country": "Oman", "total_fertility_rate": 2.48},
    {"country": "Niue", "total_fertility_rate": 2.46},
    {"country": "Honduras", "total_fertility_rate": 2.45},
    {"country": "Paraguay", "total_fertility_rate": 2.40},
    {"country": "Guyana", "total_fertility_rate": 2.37},
    {"country": "Laos", "total_fertility_rate": 2.36},
    {"country": "Saudi Arabia", "total_fertility_rate": 2.29},
    {"country": "Northern Mariana Islands (US)", "total_fertility_rate": 2.28},
    {"country": "Guatemala", "total_fertility_rate": 2.26},
    {"country": "Libya", "total_fertility_rate": 2.25},
    {"country": "Fiji", "total_fertility_rate": 2.25},
    {"country": "American Samoa (US)", "total_fertility_rate": 2.25},
    {"country": "World", "total_fertility_rate": 2.24},
    {"country": "Suriname", "total_fertility_rate": 2.21},
    {"country": "Lebanon", "total_fertility_rate": 2.21},
    {"country": "Faroe Islands (Denmark)", "total_fertility_rate": 2.20},
    {"country": "Dominican Republic", "total_fertility_rate": 2.20},
    {"country": "South Africa", "total_fertility_rate": 2.19},
    {"country": "Morocco", "total_fertility_rate": 2.18},
    {"country": "Nicaragua", "total_fertility_rate": 2.18},
    {"country": "Western Sahara", "total_fertility_rate": 2.15},
    {"country": "Réunion (France)", "total_fertility_rate": 2.13},
    {"country": "Bangladesh", "total_fertility_rate": 2.11},
    {"country": "Indonesia", "total_fertility_rate": 2.10},
    {"country": "Monaco", "total_fertility_rate": 2.09},
    {"country": "Panama", "total_fertility_rate": 2.09},
    {"country": "Seychelles", "total_fertility_rate": 2.08},
    {"country": "Myanmar", "total_fertility_rate": 2.08},
    {"country": "U.S. Virgin Islands (US)", "total_fertility_rate": 2.07},
    {"country": "Venezuela", "total_fertility_rate": 2.06},
    {"country": "Guadeloupe (France)", "total_fertility_rate": 2.05},
    {"country": "Belize", "total_fertility_rate": 2.01},
    {"country": "Cook Islands", "total_fertility_rate": 2.00},
    {"country": "Martinique (France)", "total_fertility_rate": 1.97},
    {"country": "New Caledonia (France)", "total_fertility_rate": 1.95},
    {"country": "India", "total_fertility_rate": 1.94},
    {"country": "Peru", "total_fertility_rate": 1.94},
    {"country": "Sri Lanka", "total_fertility_rate": 1.94},
    {"country": "Nepal", "total_fertility_rate": 1.94},
    {"country": "Greenland (Denmark)", "total_fertility_rate": 1.91},
    {"country": "Gibraltar (UK)", "total_fertility_rate": 1.88},
    {"country": "Vietnam", "total_fertility_rate": 1.88},
    {"country": "Philippines", "total_fertility_rate": 1.88},
    {"country": "Mexico", "total_fertility_rate": 1.87},
    {"country": "Palau", "total_fertility_rate": 1.86},
    {"country": "Tunisia", "total_fertility_rate": 1.80},
    {"country": "Montenegro", "total_fertility_rate": 1.80},
    {"country": "Ecuador", "total_fertility_rate": 1.79},
    {"country": "Georgia", "total_fertility_rate": 1.79},
    {"country": "Bahrain", "total_fertility_rate": 1.78},
    {"country": "North Korea", "total_fertility_rate": 1.77},
    {"country": "El Salvador", "total_fertility_rate": 1.75},
    {"country": "Saint Vincent and the Grenadines", "total_fertility_rate": 1.75},
    {"country": "Bulgaria", "total_fertility_rate": 1.74},
    {"country": "Moldova", "total_fertility_rate": 1.72},
    {"country": "Armenia", "total_fertility_rate": 1.71},
    {"country": "Brunei", "total_fertility_rate": 1.71},
    {"country": "Romania", "total_fertility_rate": 1.71},
    {"country": "Barbados", "total_fertility_rate": 1.71},
    {"country": "Qatar", "total_fertility_rate": 1.70},
    {"country": "Falkland Islands (UK)", "total_fertility_rate": 1.70},
    {"country": "Iran", "total_fertility_rate": 1.67},
    {"country": "Azerbaijan", "total_fertility_rate": 1.67},
    {"country": "New Zealand", "total_fertility_rate": 1.65},
    {"country": "Saint Helena, Ascension and Tristan da Cunha (UK)", "total_fertility_rate": 1.64},
    {"country": "Australia", "total_fertility_rate": 1.64},
    {"country": "France", "total_fertility_rate": 1.64},
    {"country": "United States", "total_fertility_rate": 1.62},
    {"country": "Turkey", "total_fertility_rate": 1.62},
    {"country": "Colombia", "total_fertility_rate": 1.62},
    {"country": "Aruba (Netherlands)", "total_fertility_rate": 1.61},
    {"country": "Brazil", "total_fertility_rate": 1.60},
    {"country": "Ireland", "total_fertility_rate": 1.60},
    {"country": "Slovenia", "total_fertility_rate": 1.58},
    {"country": "Antigua and Barbuda", "total_fertility_rate": 1.58},
    {"country": "Slovakia", "total_fertility_rate": 1.57},
    {"country": "Maldives", "total_fertility_rate": 1.55},
    {"country": "United Kingdom", "total_fertility_rate": 1.54},
    {"country": "Liechtenstein", "total_fertility_rate": 1.54},
    {"country": "Isle of Man (UK)", "total_fertility_rate": 1.53},
    {"country": "Malaysia", "total_fertility_rate": 1.53},
    {"country": "Kosovo", "total_fertility_rate": 1.53},
    {"country": "Trinidad and Tobago", "total_fertility_rate": 1.52},
    {"country": "Denmark", "total_fertility_rate": 1.52},
    {"country": "Portugal", "total_fertility_rate": 1.52},
    {"country": "Cayman Islands (UK)", "total_fertility_rate": 1.51},
    {"country": "Saint Kitts and Nevis", "total_fertility_rate": 1.51},
    {"country": "Argentina", "total_fertility_rate": 1.51},
    {"country": "Serbia", "total_fertility_rate": 1.50},
    {"country": "Iceland", "total_fertility_rate": 1.50},
    {"country": "Kuwait", "total_fertility_rate": 1.50},
    {"country": "Bosnia and Herzegovina", "total_fertility_rate": 1.50},
    {"country": "Cape Verde", "total_fertility_rate": 1.50},
    {"country": "Hungary", "total_fertility_rate": 1.50},
    {"country": "French Polynesia (France)", "total_fertility_rate": 1.48},
    {"country": "Croatia", "total_fertility_rate": 1.47},
    {"country": "Dominica", "total_fertility_rate": 1.47},
    {"country": "North Macedonia", "total_fertility_rate": 1.47},
    {"country": "Czech Republic", "total_fertility_rate": 1.47},
    {"country": "Russia", "total_fertility_rate": 1.47},
    {"country": "Grenada", "total_fertility_rate": 1.46},
    {"country": "Germany", "total_fertility_rate": 1.46},
    {"country": "Cuba", "total_fertility_rate": 1.45},
    {"country": "Caribbean Netherlands (Netherlands)", "total_fertility_rate": 1.45},
    {"country": "Montserrat (UK)", "total_fertility_rate": 1.45},
    {"country": "Switzerland", "total_fertility_rate": 1.44},
    {"country": "Turks and Caicos Islands (UK)", "total_fertility_rate": 1.44},
    {"country": "Sweden", "total_fertility_rate": 1.44},
    {"country": "Netherlands", "total_fertility_rate": 1.44},
    {"country": "Bhutan", "total_fertility_rate": 1.44},
    {"country": "Sint Maarten (Netherlands)", "total_fertility_rate": 1.43},
    {"country": "Norway", "total_fertility_rate": 1.42},
    {"country": "Bermuda (UK)", "total_fertility_rate": 1.41},
    {"country": "Luxembourg", "total_fertility_rate": 1.40},
    {"country": "Wallis and Futuna (France)", "total_fertility_rate": 1.40},
    {"country": "Belgium", "total_fertility_rate": 1.39},
    {"country": "Uruguay", "total_fertility_rate": 1.39},
    {"country": "Jersey (UK)", "total_fertility_rate": 1.38},
    {"country": "Estonia", "total_fertility_rate": 1.38},
    {"country": "Saint Lucia", "total_fertility_rate": 1.38},
    {"country": "Guernsey (UK)", "total_fertility_rate": 1.37},
    {"country": "Cyprus", "total_fertility_rate": 1.37},
    {"country": "Bahamas", "total_fertility_rate": 1.36},
    {"country": "Anguilla (UK)", "total_fertility_rate": 1.35},
    {"country": "Latvia", "total_fertility_rate": 1.35},
    {"country": "Greece", "total_fertility_rate": 1.34},
    {"country": "Jamaica", "total_fertility_rate": 1.34},
    {"country": "Canada", "total_fertility_rate": 1.33},
    {"country": "Albania", "total_fertility_rate": 1.33},
    {"country": "Austria", "total_fertility_rate": 1.33},
    {"country": "Costa Rica", "total_fertility_rate": 1.31},
    {"country": "Poland", "total_fertility_rate": 1.31},
    {"country": "Finland", "total_fertility_rate": 1.30},
    {"country": "Saint Pierre and Miquelon (France)", "total_fertility_rate": 1.28},
    {"country": "Japan", "total_fertility_rate": 1.23},
    {"country": "Belarus", "total_fertility_rate": 1.23},
    {"country": "Lithuania", "total_fertility_rate": 1.22},
    {"country": "Spain", "total_fertility_rate": 1.21},
    {"country": "Mauritius", "total_fertility_rate": 1.21},
    {"country": "United Arab Emirates", "total_fertility_rate": 1.21},
    {"country": "Italy", "total_fertility_rate": 1.20},
    {"country": "Thailand", "total_fertility_rate": 1.20},
    {"country": "San Marino", "total_fertility_rate": 1.16},
    {"country": "Chile", "total_fertility_rate": 1.13},
    {"country": "Malta", "total_fertility_rate": 1.11},
    {"country": "Andorra", "total_fertility_rate": 1.10},
    {"country": "Curaçao (Netherlands)", "total_fertility_rate": 1.07},
    {"country": "British Virgin Islands (UK)", "total_fertility_rate": 1.06},
    {"country": "China", "total_fertility_rate": 1.02},
    {"country": "Vatican City", "total_fertility_rate": 1.00},
    {"country": "Ukraine", "total_fertility_rate": 1.00},
    {"country": "Singapore", "total_fertility_rate": 0.96},
    {"country": "Puerto Rico (US)", "total_fertility_rate": 0.94},
    {"country": "Taiwan", "total_fertility_rate": 0.86},
    {"country": "Saint Barthélemy (France)", "total_fertility_rate": 0.83},
    {"country": "South Korea", "total_fertility_rate": 0.75},
    {"country": "Hong Kong (China)", "total_fertility_rate": 0.74},
    {"country": "Macau (China)", "total_fertility_rate": 0.69}
  ]
}